{
  "ActionWrappersClosest": {
    "selectors": [
      ".like-wrapper, .collect-wrapper"
    ],
    "states": null
  },
  "AvatarIcon": {
    "selectors": [
      ".reds-avatar",
      ".reds-avatar-img-box",
      ".user-avatar",
      ".avatar-wrapper img",
      "[data-testid=\u0027user-avatar\u0027]"
    ],
    "states": null
  },
  "CloseButton": {
    "selectors": [
      ".close-btn",
      ".modal-close",
      "button[aria-label=\u0027\u5173\u95ED\u0027]",
      "[data-testid=\u0027close-button\u0027]",
      ".icon-close"
    ],
    "states": null
  },
  "CollectIcon": {
    "selectors": [
      "svg.collect-icon",
      ".collect-wrapper svg.collect-icon",
      ".engage-bar svg.collect-icon",
      ".buttons .collect-wrapper svg.collect-icon",
      "[data-testid=\u0027favorite-button\u0027] svg"
    ],
    "states": null
  },
  "CollectWrapper": {
    "selectors": [
      "#note-page-collect-board-guide.collect-wrapper",
      ".engage-bar .collect-wrapper",
      ".collect-wrapper",
      "[data-testid=\u0027collect-wrapper\u0027]"
    ],
    "states": null
  },
  "CommentAreaExpanded": {
    "selectors": [
      ".engage-bar.active .input-box",
      ".engage-bar.active .content-edit",
      ".engage-bar.active .bottom",
      "[data-testid=\u0027comment-area-expanded\u0027]"
    ],
    "states": null
  },
  "CommentAuthorDetail": {
    "selectors": [
      ".comment-item .author .name",
      ".comment-item .author-wrapper .name",
      ".comment-inner-container .right .author .name",
      ".comment-item a.name[target=\u0027_blank\u0027]",
      "[data-testid=\u0027comment-author-detail\u0027]"
    ],
    "states": null
  },
  "CommentButton": {
    "selectors": [
      ".engage-bar .chat-wrapper:has(.chat-icon)",
      ".buttons .chat-wrapper:has(.count)",
      ".comment-btn:has-text(\u0027\u8BC4\u8BBA\u0027)",
      "button:has-text(\u0027\u8BC4\u8BBA\u0027)",
      "[data-testid=\u0027comment-button\u0027]",
      ".comment-wrapper",
      "#comment",
      ".comment-icon"
    ],
    "states": null
  },
  "CommentContentDetail": {
    "selectors": [
      ".comment-item .content .note-text span",
      ".comment-inner-container .content .note-text span",
      ".comment-item .note-text",
      ".content .note-text",
      "[data-testid=\u0027comment-content-detail\u0027]"
    ],
    "states": null
  },
  "commentCount": {
    "selectors": [
      ".engage-bar .chat-wrapper .count",
      ".buttons.engage-bar-style .chat-wrapper .count",
      ".chat-wrapper .count[selected-disabled-search]",
      ".comment-counter .count-text",
      ".interaction-stats .comment-count",
      ".engage-stats .comment-number",
      ".comments-container .total",
      "[data-testid=\u0027comment-count-display\u0027]",
      ".chat-wrapper span.count"
    ],
    "states": null
  },
  "CommentDateTime": {
    "selectors": [
      ".comment-item .date span[selected-disabled-search]",
      ".comment-item .info .date",
      ".comment-item .location",
      ".date .location",
      "[data-testid=\u0027comment-datetime\u0027]"
    ],
    "states": null
  },
  "CommentInput": {
    "selectors": [
      "textarea[placeholder*=\u0027\u8BC4\u8BBA\u0027]:not([disabled])",
      "div[contenteditable=\u0027true\u0027]:has-text(\u0027\u8BC4\u8BBA\u0027)",
      ".comment-box textarea",
      ".reply-input",
      ".comment-input",
      "[data-testid=\u0027comment-input\u0027]"
    ],
    "states": null
  },
  "CommentInputReady": {
    "selectors": [
      "#content-textarea[contenteditable=\u0027true\u0027][data-tribute=\u0027true\u0027]",
      "p.content-input[contenteditable=\u0027true\u0027]",
      ".content-edit p[contenteditable][data-tribute]",
      ".input-box .content-input[contenteditable]",
      "[data-testid=\u0027comment-input-ready\u0027]"
    ],
    "states": null
  },
  "CommentItem": {
    "selectors": [
      ".comment-item",
      ".comment-card",
      ".comment",
      "[data-testid=\u0027comment-item\u0027]",
      ".comment-wrapper"
    ],
    "states": null
  },
  "CommentItemDetail": {
    "selectors": [
      ".comment-item[id^=\u0027comment-\u0027]",
      ".parent-comment .comment-item",
      ".comment-item:not(.comment-item-sub)",
      ".comments-container .comment-item",
      "[data-testid=\u0027comment-item-detail\u0027]"
    ],
    "states": null
  },
  "CommentItemSub": {
    "selectors": [
      ".comment-item.comment-item-sub[id^=\u0027comment-\u0027]",
      ".comment-item-sub",
      ".reply-container .comment-item",
      "[data-testid=\u0027comment-item-sub\u0027]"
    ],
    "states": null
  },
  "CommentLikeCountDetail": {
    "selectors": [
      ".comment-item .like-wrapper .count",
      ".comment-item .interactions .like .count",
      ".like-wrapper.like-active .count",
      ".comment-item .like .count",
      "[data-testid=\u0027comment-like-count-detail\u0027]"
    ],
    "states": null
  },
  "CommentList": {
    "selectors": [
      ".comment-list",
      ".comments-container",
      "#comment-list",
      "[data-testid=\u0027comment-list\u0027]",
      ".comment-section"
    ],
    "states": null
  },
  "CommentReplyCount": {
    "selectors": [
      ".comment-item .reply .count",
      ".comment-item .interactions .reply .count",
      ".reply.icon-container .count",
      ".show-more",
      "[data-testid=\u0027comment-reply-count\u0027]"
    ],
    "states": null
  },
  "CommentSubmitDisabled": {
    "selectors": [
      ".right-btn-area .btn.submit.gray[disabled]",
      ".btn.submit[disabled]",
      "button.submit.gray",
      ".btn.submit:disabled",
      "[data-testid=\u0027comment-submit-disabled\u0027]"
    ],
    "states": null
  },
  "CommentSubmitEnabled": {
    "selectors": [
      ".right-btn-area .btn.submit:not([disabled])",
      ".btn.submit:not(.gray):not([disabled])",
      "button.submit:not([disabled]):not(.gray)",
      "[data-testid=\u0027comment-submit-enabled\u0027]"
    ],
    "states": null
  },
  "CommentTotal": {
    "selectors": [
      ".comments-container .total",
      ".comments-el .total",
      ".total[selected-disabled-search]",
      ".comment-total",
      "[data-testid=\u0027comment-total\u0027]"
    ],
    "states": null
  },
  "DetailMoreActions": {
    "selectors": [
      ".note-detail-mask button:has(svg use[xlink\\:href=\u0027#more\u0027])",
      ".note-detail-mask button:has(svg use[href=\u0027#more\u0027])",
      ".note-detail-mask [role=\u0027button\u0027]:has-text(\u0027\u66F4\u591A\u0027)",
      "button:has-text(\u0027\u66F4\u591A\u0027)",
      "[aria-label=\u0027\u66F4\u591A\u0027]",
      "[data-testid=\u0027detail-more-actions\u0027]"
    ],
    "states": null
  },
  "DetailPageCommentButton": {
    "selectors": [
      ".engage-bar .chat-wrapper",
      ".buttons.engage-bar-style .chat-wrapper",
      ".input-box .not-active",
      "#content-textarea",
      "[data-testid=\u0027detail-page-comment-button\u0027]"
    ],
    "states": null
  },
  "DetailPageCommentCancel": {
    "selectors": [
      ".right-btn-area .btn.cancel",
      ".bottom .btn.cancel",
      ".engage-bar .cancel",
      "[data-testid=\u0027detail-page-comment-cancel\u0027]"
    ],
    "states": null
  },
  "DetailPageCommentInput": {
    "selectors": [
      "#content-textarea[contenteditable=\u0027true\u0027]",
      ".content-input[data-tribute=\u0027true\u0027]",
      ".input-box .content-edit p[contenteditable]",
      ".engage-bar .input-box",
      "[data-testid=\u0027detail-page-comment-input\u0027]"
    ],
    "states": null
  },
  "DetailPageCommentSubmit": {
    "selectors": [
      ".right-btn-area .btn.submit",
      ".bottom .btn.submit",
      "button.submit.gray[disabled]",
      ".engage-bar .submit",
      "[data-testid=\u0027detail-page-comment-submit\u0027]"
    ],
    "states": null
  },
  "DragText": {
    "selectors": [
      ".drag-text",
      "p:has-text(\u0027\u62D6\u62FD\u56FE\u7247\u5230\u6B64\u6216\u70B9\u51FB\u4E0A\u4F20\u0027)",
      "p.drag-text",
      ".upload-hint",
      ".drag-hint-text",
      "[data-testid=\u0027drag-text\u0027]"
    ],
    "states": null
  },
  "DragUploadArea": {
    "selectors": [
      ".drag-over",
      "[data-v-7cbccdb2].drag-over",
      "[data-v-*].drag-over",
      "div.drag-over",
      ".upload-drop-zone",
      "[data-testid=\u0027drag-area\u0027]"
    ],
    "states": null
  },
  "DynamicCollectCount": {
    "selectors": [
      "#note-page-collect-board-guide .count",
      ".collect-wrapper .count",
      ".engage-bar .collect-wrapper .count",
      "[data-testid=\u0027dynamic-collect-count\u0027]"
    ],
    "states": null
  },
  "DynamicCommentCount": {
    "selectors": [
      ".engage-bar .chat-wrapper .count",
      ".buttons.engage-bar-style .chat-wrapper .count",
      ".chat-wrapper .count",
      "[data-testid=\u0027dynamic-comment-count\u0027]"
    ],
    "states": null
  },
  "DynamicFormElement": {
    "selectors": [
      "[data-dynamic=\u0027true\u0027]",
      ".dynamic-field",
      ".form-field[data-loaded=\u0027true\u0027]",
      "[data-testid*=\u0027dynamic\u0027]",
      ".vue-form-item"
    ],
    "states": null
  },
  "DynamicLikeCount": {
    "selectors": [
      ".like-wrapper.like-active .count[selected-disabled-search]",
      ".engage-bar .like-wrapper .count",
      ".buttons.engage-bar-style .like-wrapper .count",
      "[data-testid=\u0027dynamic-like-count\u0027]"
    ],
    "states": null
  },
  "EditorContainer": {
    "selectors": [
      ".editor-container",
      ".rich-editor",
      ".text-editor",
      ".vue-editor",
      ".note-editor-wrapper",
      "[data-v-*] .editor",
      "[data-testid=\u0027editor-container\u0027]",
      ".content-editor-wrapper"
    ],
    "states": null
  },
  "EditorLoading": {
    "selectors": [
      ".editor-loading",
      ".editor-spinner",
      ".content-loading",
      "[data-testid=\u0027editor-loading\u0027]",
      ".loading-editor"
    ],
    "states": null
  },
  "EditorReady": {
    "selectors": [
      ".editor-ready",
      ".editor-active",
      ".editor[data-ready=\u0027true\u0027]",
      "[data-testid=\u0027editor-ready\u0027]",
      ".content-editor.ready"
    ],
    "states": null
  },
  "EditState": {
    "selectors": [
      ".tiptap.ProseMirror",
      "input[placeholder*=\u0027\u586B\u5199\u6807\u9898\u4F1A\u6709\u66F4\u591A\u8D5E\u54E6\u0027]",
      ".editor-container",
      "[data-testid=\u0027edit-state\u0027]"
    ],
    "states": null
  },
  "EmojiClickArea": {
    "selectors": [
      ".emoji-area .click-area",
      ".recent-emoji .click-area img",
      ".emoji-area img.emoji",
      "[data-testid=\u0027emoji-click-area\u0027]"
    ],
    "states": null
  },
  "EmojiTriggerButton": {
    "selectors": [
      "#showEmojiEl",
      "svg[id=\u0027showEmojiEl\u0027]",
      ".left-icon-area .icon svg[xlink:href=\u0027#emoji\u0027]",
      "[data-testid=\u0027emoji-trigger\u0027]"
    ],
    "states": null
  },
  "EngageBarActive": {
    "selectors": [
      ".engage-bar.active",
      ".engage-bar[class*=\u0027active\u0027]",
      "div.engage-bar.active",
      "[data-testid=\u0027engage-bar-active\u0027]"
    ],
    "states": null
  },
  "ErrorMessage": {
    "selectors": [
      ".error-message",
      ".error-tip",
      ".toast-error",
      "[data-testid=\u0027error-message\u0027]",
      ".notification.error"
    ],
    "states": null
  },
  "favoriteButton": {
    "selectors": [
      "#note-page-collect-board-guide.collect-wrapper:has(use[xlink\\:href=\u0027#collect\u0027])",
      "#note-page-collect-board-guide.collect-wrapper:has(use[href=\u0027#collect\u0027])",
      ".engage-bar .collect-wrapper:has(use[xlink\\:href=\u0027#collect\u0027])",
      ".engage-bar .collect-wrapper:has(use[href=\u0027#collect\u0027])",
      ".collect-wrapper:has(use[xlink\\:href=\u0027#collect\u0027])",
      ".collect-wrapper:has(use[href=\u0027#collect\u0027])",
      "[data-testid=\u0027favorite-button\u0027]:not([aria-pressed=\u0027true\u0027])",
      ".collect-wrapper:has(.collect-icon):not(:has(use[xlink\\:href=\u0027#collected\u0027]))",
      ".collect-wrapper:has(.collect-icon):not(:has(use[href=\u0027#collected\u0027]))"
    ],
    "states": null
  },
  "favoriteButtonActive": {
    "selectors": [
      "#note-page-collect-board-guide.collect-wrapper:has(use[xlink\\:href=\u0027#collected\u0027])",
      "#note-page-collect-board-guide.collect-wrapper:has(use[href=\u0027#collected\u0027])",
      ".engage-bar .collect-wrapper:has(use[xlink\\:href=\u0027#collected\u0027])",
      ".engage-bar .collect-wrapper:has(use[href=\u0027#collected\u0027])",
      ".collect-wrapper:has(use[xlink\\:href=\u0027#collected\u0027])",
      ".collect-wrapper:has(use[href=\u0027#collected\u0027])",
      "[data-testid=\u0027favorite-button\u0027][aria-pressed=\u0027true\u0027]"
    ],
    "states": null
  },
  "favoriteButtonLoading": {
    "selectors": [
      ".collect-wrapper.loading",
      ".collect-wrapper[data-loading=\u0027true\u0027]",
      ".favorite-button.loading",
      ".favorite-container .loading",
      ".interaction-buttons .collect.loading",
      "[data-testid=\u0027favorite-button\u0027][aria-busy=\u0027true\u0027]",
      ".collect-icon.loading"
    ],
    "states": null
  },
  "favoriteCount": {
    "selectors": [
      ".engage-bar .collect-wrapper .count",
      ".collect-wrapper.collect-active .count[selected-disabled-search]",
      ".buttons.engage-bar-style .collect-wrapper .count",
      ".favorite-counter .count-text",
      ".interaction-stats .collect-count",
      ".engage-stats .collect-number",
      "[data-testid=\u0027favorite-count-display\u0027]",
      ".collect-wrapper span.count"
    ],
    "states": null
  },
  "FileInput": {
    "selectors": [
      ".upload-input",
      "input.upload-input[type=\u0027file\u0027][multiple]",
      "input[accept=\u0027.jpg,.jpeg,.png,.webp\u0027]",
      "input[type=\u0027file\u0027][multiple]",
      "input[accept*=\u0027image\u0027]",
      "input[accept*=\u0027video\u0027]",
      "[data-testid=\u0027file-input\u0027]"
    ],
    "states": null
  },
  "FilterButton": {
    "selectors": [
      ".filter",
      "span:has-text(\u0027\u7B5B\u9009\u0027)",
      "button:has-text(\u0027\u7B5B\u9009\u0027)",
      ".filter:has(.filter-icon)",
      "[aria-label*=\u0027\u7B5B\u9009\u0027]",
      "[data-testid=\u0027filter-button\u0027]"
    ],
    "states": null
  },
  "FilterOptions": {
    "selectors": [
      ".filters",
      ".filters-wrapper .filters",
      ".tag-container",
      "[data-testid=\u0027filter-options\u0027]"
    ],
    "states": null
  },
  "FilterPanel": {
    "selectors": [
      ".filter-panel",
      "div[data-v-eb91fffe=\u0027\u0027].filter-panel",
      ".filter-container",
      ".filters-wrapper",
      "[role=\u0027dialog\u0027]:has-text(\u0027\u7B5B\u9009\u0027)",
      "[data-testid=\u0027filter-panel\u0027]"
    ],
    "states": null
  },
  "ImagePreview": {
    "selectors": [
      ".image-preview",
      ".preview-container",
      ".image-list",
      ".uploaded-images",
      ".preview-wrapper",
      "[data-testid=\u0027image-preview\u0027]",
      ".image-thumbnails"
    ],
    "states": null
  },
  "ImageSelectButton": {
    "selectors": [
      ".el-button.upload-button",
      ".upload-button",
      "button:has-text(\u0027\u4E0A\u4F20\u56FE\u7247\u0027)",
      ".upload-btn",
      ".select-files",
      ".choose-image",
      "button:has-text(\u0027\u9009\u62E9\u56FE\u7247\u0027)",
      "button:has-text(\u0027\u6DFB\u52A0\u56FE\u7247\u0027)",
      "[data-testid=\u0027image-select\u0027]",
      ".file-selector-btn"
    ],
    "states": null
  },
  "ImageUploadArea": {
    "selectors": [
      ".upload-area",
      ".image-uploader",
      ".file-drop-zone",
      ".drop-zone",
      ".upload-zone",
      ".file-upload-area",
      "[data-testid=\u0027upload-area\u0027]",
      ".drag-drop-area",
      ".image-drop-area"
    ],
    "states": null
  },
  "ImageUploadWrapper": {
    "selectors": [
      ".upload-wrapper",
      "[data-v-8c223b18].upload-wrapper",
      "[data-v-*].upload-wrapper",
      "div.upload-wrapper",
      "[data-testid=\u0027upload-wrapper\u0027]"
    ],
    "states": null
  },
  "LeftIconArea": {
    "selectors": [
      ".left-icon-area",
      ".bottom-inner .left-icon-area",
      ".engage-bar .left-icon-area .icon",
      "[data-testid=\u0027left-icon-area\u0027]"
    ],
    "states": null
  },
  "likeButton": {
    "selectors": [
      ".interactions.engage-bar .buttons .left .like-wrapper:has(use[xlink\\:href=\u0027#like\u0027])",
      ".interactions.engage-bar .buttons .left .like-wrapper:has(use[href=\u0027#like\u0027])",
      ".engage-bar .like-wrapper:has(use[xlink\\:href=\u0027#like\u0027])",
      ".engage-bar .like-wrapper:has(use[href=\u0027#like\u0027])",
      ".like-wrapper:has(use[xlink\\:href=\u0027#like\u0027])",
      ".like-wrapper:has(use[href=\u0027#like\u0027])",
      "[data-testid=\u0027like-button\u0027]:not([aria-pressed=\u0027true\u0027])",
      ".like-wrapper:has(.like-icon):not(:has(use[xlink\\:href=\u0027#liked\u0027]))",
      ".like-wrapper:has(.like-icon):not(:has(use[href=\u0027#liked\u0027]))"
    ],
    "states": null
  },
  "likeButtonActive": {
    "selectors": [
      ".interactions.engage-bar .buttons .left .like-wrapper:has(use[xlink\\:href=\u0027#liked\u0027])",
      ".interactions.engage-bar .buttons .left .like-wrapper:has(use[href=\u0027#liked\u0027])",
      ".engage-bar .like-wrapper:has(use[xlink\\:href=\u0027#liked\u0027])",
      ".engage-bar .like-wrapper:has(use[href=\u0027#liked\u0027])",
      ".like-wrapper:has(use[xlink\\:href=\u0027#liked\u0027])",
      ".like-wrapper:has(use[href=\u0027#liked\u0027])",
      "[data-testid=\u0027like-button\u0027][aria-pressed=\u0027true\u0027]"
    ],
    "states": null
  },
  "likeButtonLoading": {
    "selectors": [
      ".like-wrapper.loading",
      ".like-wrapper[data-loading=\u0027true\u0027]",
      ".like-button.loading",
      ".like-container .loading",
      ".interaction-buttons .like.loading",
      "[data-testid=\u0027like-button\u0027][aria-busy=\u0027true\u0027]",
      ".like-icon.loading"
    ],
    "states": null
  },
  "likeCount": {
    "selectors": [
      ".engage-bar .like-wrapper .count",
      ".like-wrapper.like-active .count[selected-disabled-search]",
      ".buttons.engage-bar-style .like-wrapper .count",
      ".like-counter .count-text",
      ".interaction-stats .like-count",
      ".engage-stats .like-number",
      "[data-testid=\u0027like-count-display\u0027]",
      ".like-wrapper span.count"
    ],
    "states": null
  },
  "LikeIcon": {
    "selectors": [
      "svg.like-icon",
      ".like-wrapper svg.like-icon",
      ".engage-bar svg.like-icon",
      ".buttons .like-wrapper svg.like-icon",
      "[data-testid=\u0027like-button\u0027] svg"
    ],
    "states": null
  },
  "LikeWrapper": {
    "selectors": [
      ".interactions.engage-bar .buttons .left .like-wrapper",
      ".engage-bar .like-wrapper",
      ".like-wrapper",
      "[data-testid=\u0027like-wrapper\u0027]"
    ],
    "states": null
  },
  "LoadingIndicator": {
    "selectors": [
      ".loading",
      ".spinner",
      ".loading-wrapper",
      "[data-testid=\u0027loading\u0027]",
      ".lds-ring"
    ],
    "states": null
  },
  "LocationSelector": {
    "selectors": [
      ".location-selector",
      ".place-selector",
      "input[placeholder*=\u0027\u4F4D\u7F6E\u0027]",
      "input[placeholder*=\u0027\u5730\u70B9\u0027]",
      "[data-testid=\u0027location-input\u0027]",
      ".location-input"
    ],
    "states": null
  },
  "LoginButton": {
    "selectors": [
      "#login-btn",
      ".side-bar-component.login-btn button#login-btn",
      ".reds-button-new.login-btn",
      "button.login-btn[id=\u0027login-btn\u0027]",
      ".login-btn",
      "button:has-text(\u0027\u767B\u5F55\u0027)",
      "[data-testid=\u0027login-button\u0027]",
      "button[type=\u0027button\u0027]:has-text(\u0027\u767B\u5F55\u0027)",
      ".auth-btn.primary"
    ],
    "states": null
  },
  "MainScrollContainer": {
    "selectors": [
      "#exploreFeeds",
      ".channel-container",
      ".search-layout__main",
      ".search-content",
      ".result-list",
      ".note-list, .note-feed",
      "main[role=\u0027main\u0027]",
      "main .content, main .container",
      ".home-layout__main",
      "main",
      "body"
    ],
    "states": null
  },
  "MentionTriggerButton": {
    "selectors": [
      "#showMentionEl",
      "svg[id=\u0027showMentionEl\u0027]",
      ".left-icon-area .icon svg[xlink:href=\u0027#mention\u0027]",
      "[data-testid=\u0027mention-trigger\u0027]"
    ],
    "states": null
  },
  "Modal": {
    "selectors": [
      ".modal",
      ".dialog",
      ".popup",
      "[data-testid=\u0027modal\u0027]",
      ".overlay-container"
    ],
    "states": null
  },
  "NoteAuthor": {
    "selectors": [
      ".card-bottom-wrapper .author .name",
      ".author-wrapper .author .name",
      ".card-bottom-wrapper .name span.name",
      ".author .name",
      ".author span.name",
      ".name",
      ".user-name",
      ".author",
      ".note-author-name",
      ".creator-name",
      "[data-testid=\u0027note-author\u0027]"
    ],
    "states": null
  },
  "NoteContent": {
    "selectors": [
      ".note-content",
      ".desc",
      "#note-content",
      "[data-testid=\u0027note-content\u0027]",
      ".note-text"
    ],
    "states": null
  },
  "NoteCoverImage": {
    "selectors": [
      ".cover img[data-xhs-img]",
      "a.cover.mask.ld img",
      ".cover img[elementtiming=\u0027card-exposed\u0027]",
      "img[src*=\u0027sns-webpic-qc.xhscdn.com\u0027]",
      ".cover img",
      "a.cover img",
      "[data-testid=\u0027cover-image\u0027]"
    ],
    "states": null
  },
  "NoteDetailAuthor": {
    "selectors": [
      ".author-wrapper .info .name .username",
      ".author .info .name .username",
      ".username",
      ".author-wrapper .name",
      ".info .name",
      "[data-testid=\u0027note-detail-author\u0027]"
    ],
    "states": null
  },
  "NoteDetailAuthorAvatar": {
    "selectors": [
      ".author-wrapper .info a img.avatar-item",
      ".author .info img.avatar-item",
      ".avatar-item[crossorigin=\u0027anonymous\u0027]",
      ".info a img",
      "[data-testid=\u0027note-detail-avatar\u0027]"
    ],
    "states": null
  },
  "NoteDetailCloseButton": {
    "selectors": [
      ".close-circle .close",
      ".close-box",
      ".close-circle",
      ".close.close-mask-dark",
      "[data-testid=\u0027note-detail-close\u0027]"
    ],
    "states": null
  },
  "NoteDetailModal": {
    "selectors": [
      ".note-detail-mask[note-id]",
      ".note-detail-mask",
      "[note-id]",
      "#noteContainer",
      ".note-container[data-type=\u0027normal\u0027]",
      "[data-testid=\u0027note-detail-modal\u0027]"
    ],
    "states": null
  },
  "NoteDetailTitle": {
    "selectors": [
      "#detail-desc:has(.note-text span) .note-text span",
      "#detail-desc .note-text span",
      "#detail-desc .desc .note-text span",
      ".desc .note-text span",
      "#detail-desc",
      "[data-testid=\u0027note-detail-title\u0027]"
    ],
    "states": null
  },
  "NoteHiddenLink": {
    "selectors": [
      "section.note-item:has(a[href*=\u0027/explore/\u0027]) a[href*=\u0027/explore/\u0027]",
      "a[style*=\u0027display: none\u0027]",
      "a[href*=\u0027/explore/\u0027][style*=\u0027none\u0027]",
      "section a:first-child[style*=\u0027display\u0027]",
      "[data-testid=\u0027hidden-link\u0027]"
    ],
    "states": null
  },
  "NoteItem": {
    "selectors": [
      "section.note-item",
      "[data-v-a264b01a].note-item",
      "[data-v-330d9cca].note-item",
      ".note-item[data-width][data-height]",
      ".note-item",
      ".query-note-item",
      ".feed-item",
      "[data-testid=\u0027note-item\u0027]"
    ],
    "states": {
      "Explore": [
        "#exploreFeeds .note-item",
        "[data-v-a264b01a].note-item",
        ".channel-container .note-item",
        ".note-item[data-index]",
        ".note-item"
      ],
      "SearchResult": [
        ".search-layout__main .note-item",
        "[data-v-330d9cca].note-item",
        ".search-content .note-item",
        ".result-list .note-item",
        ".note-item"
      ]
    }
  },
  "NoteTime": {
    "selectors": [
      ".time span.time",
      ".card-bottom-wrapper .time",
      "[data-v-11fd8d4e] .time span",
      ".author-wrapper .time",
      ".time",
      ".publish-time",
      "[data-time]",
      ".note-time",
      ".date",
      ".timestamp",
      "[data-testid=\u0027note-time\u0027]"
    ],
    "states": null
  },
  "NoteTitle": {
    "selectors": [
      ".title span",
      ".footer .title",
      "a.title span[data-v-51ec0135]",
      "a.title",
      ".title",
      ".hotspot-title",
      "a[title]",
      ".note-title",
      "[data-testid=\u0027note-title\u0027]"
    ],
    "states": null
  },
  "NoteTypeImage": {
    "selectors": [
      ".tags:has(span:has-text(\u0027\u56FE\u6587\u0027))",
      ".reds-tab-item:has-text(\u0027\u56FE\u6587\u0027)",
      "[role=\u0027tab\u0027]:has-text(\u0027\u56FE\u6587\u0027)",
      "span:has-text(\u0027\u56FE\u6587\u0027)",
      "[data-testid=\u0027note-type-image\u0027]"
    ],
    "states": null
  },
  "NoteTypeVideo": {
    "selectors": [
      ".tags:has(span:has-text(\u0027\u89C6\u9891\u0027))",
      ".reds-tab-item:has-text(\u0027\u89C6\u9891\u0027)",
      "[role=\u0027tab\u0027]:has-text(\u0027\u89C6\u9891\u0027)",
      "span:has-text(\u0027\u89C6\u9891\u0027)",
      "[data-testid=\u0027note-type-video\u0027]"
    ],
    "states": null
  },
  "NoteVisibleLink": {
    "selectors": [
      ".note-item:has(a[href*=\u0027/explore/\u0027]) a[href*=\u0027/explore/\u0027]:not([style*=\u0027display: none\u0027])",
      "a.cover:has(img)",
      "a.cover.mask.ld",
      "a.cover[target=\u0027_self\u0027]",
      "a[href*=\u0027/search_result/\u0027]",
      "a[href*=\u0027/explore/\u0027]",
      ".note-item a[href]",
      "[data-testid=\u0027visible-link\u0027]"
    ],
    "states": null
  },
  "PageContainer": {
    "selectors": [],
    "states": {
      "Explore": [
        "#exploreFeeds",
        ".channel-container",
        "[data-testid=\u0027explore-page\u0027]"
      ],
      "SearchResult": [
        ".search-layout",
        ".search-layout__main",
        "[data-testid=\u0027search-result-page\u0027]"
      ]
    }
  },
  "PublishButton": {
    "selectors": [
      ".publishBtn",
      "button:has-text(\u0027\u53D1\u5E03\u0027)",
      ".publish-btn",
      ".submit-btn",
      "button:has-text(\u0027\u7ACB\u5373\u53D1\u5E03\u0027)",
      "button[type=\u0027submit\u0027]",
      "[data-testid=\u0027publish-button\u0027]",
      ".btn-publish",
      ".publish-submit"
    ],
    "states": null
  },
  "PublishContainer": {
    "selectors": [
      ".publish-container",
      ".create-note",
      ".publisher-wrapper",
      "#publish-page",
      "[data-testid=\u0027publish-container\u0027]",
      ".note-editor",
      "[data-v-*]",
      ".vue-publish-container"
    ],
    "states": null
  },
  "PublishContentInput": {
    "selectors": [
      ".tiptap.ProseMirror",
      "[contenteditable=\u0027true\u0027]",
      "div[contenteditable=\u0027true\u0027][role=\u0027textbox\u0027]",
      ".tiptap",
      ".ProseMirror",
      ".content-editor",
      ".rich-text-editor",
      ".editor-content",
      "textarea[placeholder*=\u0027\u5185\u5BB9\u0027]",
      "textarea[placeholder*=\u0027\u5206\u4EAB\u4F60\u7684\u751F\u6D3B\u0027]",
      "[data-testid=\u0027content-input\u0027]"
    ],
    "states": null
  },
  "PublishTagInput": {
    "selectors": [
      ".tag-input",
      ".hashtag-input",
      ".topic-input",
      "input[placeholder*=\u0027\u6807\u7B7E\u0027]",
      "input[placeholder*=\u0027\u8BDD\u9898\u0027]",
      "input[placeholder*=\u0027\u6DFB\u52A0\u6807\u7B7E\u0027]",
      "[data-testid=\u0027tag-input\u0027]",
      ".tag-selector",
      ".topic-selector",
      "[data-v-*] .tag-input"
    ],
    "states": null
  },
  "PublishTitleInput": {
    "selectors": [
      "input[placeholder*=\u0027\u586B\u5199\u6807\u9898\u4F1A\u6709\u66F4\u591A\u8D5E\u54E6\u0027]",
      ".d-text",
      ".title-input",
      ".note-title",
      "input[placeholder*=\u0027\u6807\u9898\u0027]",
      "input[placeholder*=\u0027\u8BF7\u8F93\u5165\u6807\u9898\u0027]",
      "#note-title-input",
      "[data-testid=\u0027title-input\u0027]",
      ".note-title-editor",
      "[data-v-*] input[type=\u0027text\u0027]"
    ],
    "states": null
  },
  "RecentEmojiArea": {
    "selectors": [
      ".emoji-area.recent-emoji",
      "[class*=\u0027emoji-area\u0027][class*=\u0027recent\u0027]",
      ".recent-emoji .click-area",
      "[data-testid=\u0027recent-emoji-area\u0027]"
    ],
    "states": null
  },
  "RightButtonArea": {
    "selectors": [
      ".right-btn-area",
      ".bottom-inner .right-btn-area",
      ".engage-bar .right-btn-area",
      "[data-testid=\u0027right-button-area\u0027]"
    ],
    "states": null
  },
  "SearchButton": {
    "selectors": [
      ".input-button .search-icon",
      ".search-icon",
      ".input-button button",
      "button.search-btn, .search-btn",
      "button[aria-label*=\u0027\u641C\u7D22\u0027]",
      "button:has-text(\u0027\u641C\u7D22\u0027)",
      "form[role=\u0027search\u0027] button",
      "[data-testid=\u0027search-button\u0027]",
      ".input-button"
    ],
    "states": null
  },
  "SearchInput": {
    "selectors": [
      "#search-input",
      ".search-input",
      "input[placeholder=\u0027\u641C\u7D22\u5C0F\u7EA2\u4E66\u0027]",
      ".input-box input",
      "input[placeholder*=\u0027\u641C\u7D22\u0027]",
      "input[type=\u0027search\u0027]:not([disabled])",
      "form[role=\u0027search\u0027] input",
      "input[aria-label*=\u0027\u641C\u7D22\u0027]",
      "input[title*=\u0027\u641C\u7D22\u0027]",
      "[data-testid=\u0027search-input\u0027]"
    ],
    "states": {
      "Explore": [
        ".search-bar .search-input",
        "#search-input",
        ".input-box input"
      ],
      "SearchResult": [
        ".search-layout .search-input",
        ".search-header .search-input",
        "#search-input",
        ".input-box input"
      ]
    }
  },
  "ShareButtonHovered": {
    "selectors": [
      ".share-icon-container.hovered",
      ".share-wrapper .hovered",
      ".share-icon-container:hover",
      "[data-testid=\u0027share-button-hovered\u0027]"
    ],
    "states": null
  },
  "SidebarDiscoverLink": {
    "selectors": [
      "a[href*=\u0027/explore?channel_id=homefeed_recommend\u0027]",
      "a[href*=\u0027/explore\u0027][href*=\u0027channel_id\u0027]",
      "a[href=\u0027/explore?channel_id=homefeed_recommend\u0027]",
      "nav a[href*=\u0027/explore\u0027]",
      ".sidebar a[href*=\u0027/explore\u0027]",
      "a:has-text(\u0027\u53D1\u73B0\u0027)",
      "a:has-text(\u0027\u63A2\u7D22\u0027)",
      "a:has-text(\u0027Recommend\u0027)",
      "[data-v-*] a[href*=\u0027explore\u0027]",
      ".nav-item a[href*=\u0027explore\u0027]",
      ".menu-item a[href*=\u0027explore\u0027]",
      "#explore-guide-refresh a",
      "[aria-label*=\u0027\u53D1\u73B0\u0027]",
      "[aria-label*=\u0027\u63A2\u7D22\u0027]",
      "[title*=\u0027\u53D1\u73B0\u0027]",
      "[title*=\u0027\u63A2\u7D22\u0027]",
      "[data-testid=\u0027sidebar-discover\u0027]",
      "[data-testid=\u0027explore-link\u0027]",
      ".discovery-link",
      ".explore-link"
    ],
    "states": null
  },
  "SidebarNavItem": {
    "selectors": [
      ".channel-list-content li",
      ".side-bar-component",
      ".link-wrapper",
      ".bottom-channel",
      "[data-testid=\u0027sidebar-nav-item\u0027]"
    ],
    "states": null
  },
  "SidebarPublishButton": {
    "selectors": [
      "a[href*=\u0027creator.xiaohongshu.com/publish/publish?source=official\u0027]",
      "a[target=\u0027_blank\u0027][href*=\u0027publish\u0027]",
      ".link-wrapper[href*=\u0027creator.xiaohongshu.com\u0027]",
      "a:has-text(\u0027\u53D1\u5E03\u0027)",
      "[data-testid=\u0027sidebar-publish\u0027]"
    ],
    "states": null
  },
  "SidebarUserProfile": {
    "selectors": [
      "a[href*=\u0027/user/profile/\u0027]",
      ".user.side-bar-component a.link-wrapper",
      "a:has(.reds-avatar)",
      ".link-wrapper:has(.reds-image-container)",
      "[data-testid=\u0027sidebar-user-profile\u0027]"
    ],
    "states": null
  },
  "SortOptionComprehensive": {
    "selectors": [
      ".tags:has(span:has-text(\u0027\u7EFC\u5408\u0027))",
      ".reds-tab-item:has-text(\u0027\u7EFC\u5408\u0027)",
      "[role=\u0027tab\u0027]:has-text(\u0027\u7EFC\u5408\u0027)",
      "span:has-text(\u0027\u7EFC\u5408\u0027)",
      "[data-testid=\u0027sort-comprehensive\u0027]"
    ],
    "states": null
  },
  "SortOptionLatest": {
    "selectors": [
      ".tags:has(span:has-text(\u0027\u6700\u65B0\u0027))",
      ".reds-tab-item:has-text(\u0027\u6700\u65B0\u0027)",
      "[role=\u0027tab\u0027]:has-text(\u0027\u6700\u65B0\u0027)",
      "span:has-text(\u0027\u6700\u65B0\u0027)",
      "[data-testid=\u0027sort-latest\u0027]"
    ],
    "states": null
  },
  "SortOptionMostCommented": {
    "selectors": [
      ".tags:has(span:has-text(\u0027\u6700\u591A\u8BC4\u8BBA\u0027))",
      ".reds-tab-item:has-text(\u0027\u6700\u591A\u8BC4\u8BBA\u0027)",
      "[role=\u0027tab\u0027]:has-text(\u0027\u6700\u591A\u8BC4\u8BBA\u0027)",
      "span:has-text(\u0027\u6700\u591A\u8BC4\u8BBA\u0027)",
      "[data-testid=\u0027sort-most-commented\u0027]"
    ],
    "states": null
  },
  "SortOptionMostFavorited": {
    "selectors": [
      ".tags:has(span:has-text(\u0027\u6700\u591A\u6536\u85CF\u0027))",
      ".reds-tab-item:has-text(\u0027\u6700\u591A\u6536\u85CF\u0027)",
      "[role=\u0027tab\u0027]:has-text(\u0027\u6700\u591A\u6536\u85CF\u0027)",
      "span:has-text(\u0027\u6700\u591A\u6536\u85CF\u0027)",
      "[data-testid=\u0027sort-most-favorited\u0027]"
    ],
    "states": null
  },
  "SortOptionMostLiked": {
    "selectors": [
      ".tags:has(span:has-text(\u0027\u6700\u591A\u70B9\u8D5E\u0027))",
      ".reds-tab-item:has-text(\u0027\u6700\u591A\u70B9\u8D5E\u0027)",
      "[role=\u0027tab\u0027]:has-text(\u0027\u6700\u591A\u70B9\u8D5E\u0027)",
      "span:has-text(\u0027\u6700\u591A\u70B9\u8D5E\u0027)",
      "[data-testid=\u0027sort-most-liked\u0027]"
    ],
    "states": null
  },
  "SortTags": {
    "selectors": [
      ".tag-container .tags",
      ".tags",
      ".tags.active",
      ".tags:has(span)",
      ".reds-tabs-list .reds-tab-item",
      "[role=\u0027tab\u0027]",
      "[data-testid=\u0027sort-tags\u0027]"
    ],
    "states": null
  },
  "SubmitButton": {
    "selectors": [
      ".submit-btn",
      "button[type=\u0027submit\u0027]",
      ".publish-btn",
      "button:has-text(\u0027\u53D1\u5E03\u0027)",
      "[data-testid=\u0027submit-button\u0027]"
    ],
    "states": null
  },
  "SuccessMessage": {
    "selectors": [
      ".success-message",
      ".success-tip",
      ".toast-success",
      "[data-testid=\u0027success-message\u0027]",
      ".notification.success"
    ],
    "states": null
  },
  "TemporarySaveButton": {
    "selectors": [
      ".cancelBtn",
      "button:has-text(\u0027\u6682\u5B58\u79BB\u5F00\u0027)",
      "button:has-text(\u0027\u6682\u5B58\u0027)",
      ".temp-save-btn",
      ".leave-btn",
      "[data-testid=\u0027temporary-save\u0027]",
      ".temp-leave-btn",
      ".draft-leave-btn"
    ],
    "states": null
  },
  "UploadButton": {
    "selectors": [
      ".el-button.upload-button",
      ".upload-button",
      "button:has-text(\u0027\u4E0A\u4F20\u56FE\u7247\u0027)",
      ".el-button[aria-disabled=\u0027false\u0027]",
      "button.upload-button",
      "[data-testid=\u0027upload-button\u0027]"
    ],
    "states": null
  },
  "UploadInfo": {
    "selectors": [
      ".info",
      "p:has-text(\u0027\u6700\u591A\u652F\u6301\u4E0A\u4F2018\u5F20\u0027)",
      "p.info",
      ".upload-limit-info",
      ".upload-tip",
      "[data-testid=\u0027upload-info\u0027]"
    ],
    "states": null
  },
  "UploadProgress": {
    "selectors": [
      ".upload-progress",
      ".progress-bar",
      ".uploading",
      ".upload-status",
      "[data-testid=\u0027upload-progress\u0027]",
      ".progress-indicator"
    ],
    "states": null
  },
  "UploadState": {
    "selectors": [
      ".upload-wrapper",
      ".drag-over",
      ".el-button.upload-button",
      "p:has-text(\u0027\u62D6\u62FD\u56FE\u7247\u5230\u6B64\u6216\u70B9\u51FB\u4E0A\u4F20\u0027)",
      "[data-testid=\u0027upload-state\u0027]"
    ],
    "states": null
  },
  "UserDescription": {
    "selectors": [
      ".user-desc",
      "div.user-desc[data-v-4947d265]",
      ".info-part .user-desc",
      "[data-testid=\u0027user-description\u0027]"
    ],
    "states": null
  },
  "UserFollowButton": {
    "selectors": [
      ".info-right-area .follow-button",
      "button.reds-button-new.follow-button",
      "button:has-text(\u0027\u5173\u6CE8\u0027)",
      ".reds-button-new.primary.follow-button",
      "[data-testid=\u0027follow-button\u0027]"
    ],
    "states": null
  },
  "UserFollowersCount": {
    "selectors": [
      ".user-interactions div:nth-child(2) .count",
      "span.count:has(\u002B span.shows:has-text(\u0027\u7C89\u4E1D\u0027))",
      "[data-testid=\u0027followers-count\u0027]"
    ],
    "states": null
  },
  "UserFollowingCount": {
    "selectors": [
      ".user-interactions div:nth-child(1) .count",
      "span.count:has(\u002B span.shows:has-text(\u0027\u5173\u6CE8\u0027))",
      ".user-interactions .count:first-child",
      "[data-testid=\u0027following-count\u0027]"
    ],
    "states": null
  },
  "UserInfo": {
    "selectors": [
      ".user-name",
      ".author",
      ".user-info",
      ".user-profile-info",
      "[data-testid=\u0027user-info\u0027]"
    ],
    "states": null
  },
  "UserLikesCollectsCount": {
    "selectors": [
      ".user-interactions div:nth-child(3) .count",
      "span.count:has(\u002B span.shows:has-text(\u0027\u83B7\u8D5E\u4E0E\u6536\u85CF\u0027))",
      "[data-testid=\u0027likes-collects-count\u0027]"
    ],
    "states": null
  },
  "UserMoreActions": {
    "selectors": [
      ".info-right-area-more-container svg",
      "svg use[xlink:href=\u0027#more\u0027]",
      ".report-entrance-wrapper svg",
      "[data-testid=\u0027user-more-actions\u0027]"
    ],
    "states": null
  },
  "UserPageAvatar": {
    "selectors": [
      ".user .user-info .avatar img.user-image",
      ".avatar-wrapper img.user-image[crossorigin=\u0027anonymous\u0027]",
      "img[src*=\u0027sns-avatar-qc.xhscdn.com\u0027]",
      ".user-image[data-xhs-img]",
      ".user-info .avatar img",
      "[data-testid=\u0027user-page-avatar\u0027]"
    ],
    "states": null
  },
  "UserPageContainer": {
    "selectors": [
      "#userPageContainer.user-page",
      ".user-page[data-csr-exp=\u0027false\u0027]",
      "div[id=\u0027userPageContainer\u0027]",
      ".user-page",
      "[data-testid=\u0027user-page\u0027]"
    ],
    "states": null
  },
  "UserPageEmptyContent": {
    "selectors": [
      ".empty-container .empty",
      "svg[xlink:href=\u0027#user_empty_collect\u0027]",
      ".empty-text:has-text(\u0027\u8FD8\u6CA1\u6709\u53D1\u5E03\u4EFB\u4F55\u5185\u5BB9\u0027)",
      ".empty-text:has-text(\u0027\u8FD8\u6CA1\u6709\u6536\u85CF\u4EFB\u4F55\u5185\u5BB9\u0027)",
      "[data-testid=\u0027empty-content\u0027]"
    ],
    "states": null
  },
  "UserPageName": {
    "selectors": [
      ".user-basic .user-nickname .user-name",
      ".basic-info .user-basic .user-name",
      ".user-nickname .user-name",
      ".user-name:not(.verify-icon)",
      ".user-name",
      "[data-testid=\u0027user-page-name\u0027]"
    ],
    "states": null
  },
  "UserPageTabs": {
    "selectors": [
      ".reds-tabs-list .reds-tab-item",
      ".tertiary.center.reds-tabs-list .reds-tab-item",
      ".reds-tab-item.active",
      ".sub-tab-list span:has-text(\u0027\u7B14\u8BB0\u0027)",
      ".sub-tab-list span:has-text(\u0027\u6536\u85CF\u0027)",
      "[data-testid=\u0027user-page-tabs\u0027]"
    ],
    "states": null
  },
  "UserRedId": {
    "selectors": [
      ".user-content .user-redId",
      "span.user-redId",
      "span:has-text(\u0027\u5C0F\u7EA2\u4E66\u53F7\uFF1A\u0027)",
      "[data-testid=\u0027user-red-id\u0027]"
    ],
    "states": null
  },
  "UserStatistics": {
    "selectors": [
      ".data-info .user-interactions",
      "div.user-interactions[data-v-18b45ae8]",
      ".user-interactions",
      "[data-testid=\u0027user-statistics\u0027]"
    ],
    "states": null
  },
  "UserVerifyIcon": {
    "selectors": [
      ".user-name .verify-icon svg",
      "span.verify-icon[data-v-1d90bc98] svg",
      ".verify-icon svg[xlink:href=\u0027#company\u0027]",
      "svg use[xlink:href=\u0027#company\u0027]",
      "[data-testid=\u0027user-verify-icon\u0027]"
    ],
    "states": null
  },
  "VueDataElement": {
    "selectors": [
      "[v-model]",
      "[v-bind]",
      "[data-v-*]",
      ".v-enter",
      ".v-leave",
      "[data-testid*=\u0027vue\u0027]"
    ],
    "states": null
  },
  "WrapperCountText": {
    "selectors": [
      ".count",
      "span.count"
    ],
    "states": null
  },
  "WrapperIconUse": {
    "selectors": [
      "svg use",
      "use"
    ],
    "states": null
  }
}